W_Python/W_tools.py
W_Python/__init__.py
W__Python/W_tools.py
W__Python/__init__.py
W_Python-0.0.0.dist-info/METADATA
W_Python-0.0.0.dist-info/WHEEL
W_Python-0.0.0.dist-info/top_level.txt
W_Python-0.0.0.dist-info/RECORD
